calculating_distributions
