Metadata-Version: 1.0
Name: calculating-distributions
Version: 1.3
Summary: Gaussian and Binomial Distributions
Home-page: UNKNOWN
Author: Rodrigo Guarneros
Author-email: rodrigo.guarneros@gmail.com
License: UNKNOWN
Platform: UNKNOWN
